odoo/addons/account_invoice_recipient_bank_currency/README.rst
odoo/addons/account_invoice_recipient_bank_currency/__init__.py
odoo/addons/account_invoice_recipient_bank_currency/__manifest__.py
odoo/addons/account_invoice_recipient_bank_currency/i18n/account_invoice_recipient_bank_currency.pot
odoo/addons/account_invoice_recipient_bank_currency/i18n/it.po
odoo/addons/account_invoice_recipient_bank_currency/models/__init__.py
odoo/addons/account_invoice_recipient_bank_currency/models/account_move.py
odoo/addons/account_invoice_recipient_bank_currency/readme/CONTRIBUTORS.rst
odoo/addons/account_invoice_recipient_bank_currency/readme/DESCRIPTION.rst
odoo/addons/account_invoice_recipient_bank_currency/static/description/icon.png
odoo/addons/account_invoice_recipient_bank_currency/static/description/index.html
odoo/addons/account_invoice_recipient_bank_currency/tests/__init__.py
odoo/addons/account_invoice_recipient_bank_currency/tests/test_account_invoice_recipient_bank_currency.py
odoo_addon_account_invoice_recipient_bank_currency-16.0.1.0.0.6.dist-info/METADATA
odoo_addon_account_invoice_recipient_bank_currency-16.0.1.0.0.6.dist-info/WHEEL
odoo_addon_account_invoice_recipient_bank_currency-16.0.1.0.0.6.dist-info/top_level.txt
odoo_addon_account_invoice_recipient_bank_currency-16.0.1.0.0.6.dist-info/RECORD
